pyembroidery/A100Reader.py
pyembroidery/A10oReader.py
pyembroidery/ArtReader.py
pyembroidery/BroReader.py
pyembroidery/ColReader.py
pyembroidery/ColWriter.py
pyembroidery/CsvReader.py
pyembroidery/CsvWriter.py
pyembroidery/DatReader.py
pyembroidery/DsbReader.py
pyembroidery/DstReader.py
pyembroidery/DstWriter.py
pyembroidery/DszReader.py
pyembroidery/EdrReader.py
pyembroidery/EdrWriter.py
pyembroidery/EmbCompress.py
pyembroidery/EmbConstant.py
pyembroidery/EmbEncoder.py
pyembroidery/EmbFunctions.py
pyembroidery/EmbMatrix.py
pyembroidery/EmbPattern.py
pyembroidery/EmbThread.py
pyembroidery/EmbThreadHus.py
pyembroidery/EmbThreadJef.py
pyembroidery/EmbThreadPec.py
pyembroidery/EmbThreadSew.py
pyembroidery/EmbThreadShv.py
pyembroidery/EmdReader.py
pyembroidery/ExpReader.py
pyembroidery/ExpWriter.py
pyembroidery/ExyReader.py
pyembroidery/FxyReader.py
pyembroidery/GcodeReader.py
pyembroidery/GcodeWriter.py
pyembroidery/GenericWriter.py
pyembroidery/GtReader.py
pyembroidery/HusReader.py
pyembroidery/InbReader.py
pyembroidery/InfReader.py
pyembroidery/InfWriter.py
pyembroidery/JefReader.py
pyembroidery/JefWriter.py
pyembroidery/JpxReader.py
pyembroidery/JsonReader.py
pyembroidery/JsonWriter.py
pyembroidery/KsmReader.py
pyembroidery/MaxReader.py
pyembroidery/MitReader.py
pyembroidery/NewReader.py
pyembroidery/PcdReader.py
pyembroidery/PcmReader.py
pyembroidery/PcqReader.py
pyembroidery/PcsReader.py
pyembroidery/PecGraphics.py
pyembroidery/PecReader.py
pyembroidery/PecWriter.py
pyembroidery/PesReader.py
pyembroidery/PesWriter.py
pyembroidery/PhbReader.py
pyembroidery/PhcReader.py
pyembroidery/PmvReader.py
pyembroidery/PmvWriter.py
pyembroidery/PngWriter.py
pyembroidery/PyEmbroidery.py
pyembroidery/ReadHelper.py
pyembroidery/SewReader.py
pyembroidery/ShvReader.py
pyembroidery/SpxReader.py
pyembroidery/StcReader.py
pyembroidery/StxReader.py
pyembroidery/SvgWriter.py
pyembroidery/TapReader.py
pyembroidery/TbfReader.py
pyembroidery/TbfWriter.py
pyembroidery/TxtWriter.py
pyembroidery-1.5.0.dist-info/LICENSE
pyembroidery-1.5.0.dist-info/METADATA
pyembroidery-1.5.0.dist-info/WHEEL
pyembroidery-1.5.0.dist-info/top_level.txt
pyembroidery-1.5.0.dist-info/RECORD
